keplar_api/__init__.py
keplar_api/api_client.py
keplar_api/api_response.py
keplar_api/configuration.py
keplar_api/exceptions.py
keplar_api/py.typed
keplar_api/rest.py
keplar_api/api/__init__.py
keplar_api/api/default_api.py
keplar_api/models/__init__.py
keplar_api/models/add_user_to_workspace_request.py
keplar_api/models/add_workspace_member_request.py
keplar_api/models/analyze_notebook200_response.py
keplar_api/models/analyze_notebook200_response_search_results.py
keplar_api/models/analyze_notebook200_response_search_results_messages_inner.py
keplar_api/models/analyze_notebook200_response_search_results_messages_inner_context_messages_inner.py
keplar_api/models/analyze_notebook_request.py
keplar_api/models/api_demos_create_demo_invite_post_request.py
keplar_api/models/api_files_file_id_signed_url_post200_response.py
keplar_api/models/api_files_file_id_signed_url_post_request.py
keplar_api/models/api_invites_id_participant_invites_get200_response.py
keplar_api/models/api_invites_id_participant_invites_participant_id_put_request.py
keplar_api/models/api_invites_id_participant_invites_post_request.py
keplar_api/models/api_invites_id_participant_invites_post_request_participant.py
keplar_api/models/api_invites_id_put_request.py
keplar_api/models/api_invites_id_responses_post_request.py
keplar_api/models/api_invites_id_responses_response_id_put_request.py
keplar_api/models/api_invites_post_request.py
keplar_api/models/api_projects_post_request.py
keplar_api/models/api_projects_post_request_thread_assets_inner.py
keplar_api/models/api_projects_project_id_analysis_post200_response.py
keplar_api/models/api_projects_project_id_analysis_post_request.py
keplar_api/models/api_projects_project_id_files_file_id_put_request.py
keplar_api/models/api_projects_project_id_files_get200_response.py
keplar_api/models/api_projects_project_id_files_post_request.py
keplar_api/models/api_projects_project_id_put_request.py
keplar_api-0.0.567804984.dist-info/METADATA
keplar_api-0.0.567804984.dist-info/WHEEL
keplar_api-0.0.567804984.dist-info/top_level.txt
keplar_api-0.0.567804984.dist-info/RECORD
